__init__.py
agents/__init__.py
agents/base.py
agents/prompts.py
agents/requirement_agent.py
agents/testcase_agent.py
app/__init__.py
app/interface.py
app/testcase_gen_app.py
core/__init__.py
core/config.py
core/logging.py
utils/__init__.py
utils/document_processor.py
testcase_gen_tool-1.0.1.dist-info/METADATA
testcase_gen_tool-1.0.1.dist-info/WHEEL
testcase_gen_tool-1.0.1.dist-info/entry_points.txt
testcase_gen_tool-1.0.1.dist-info/top_level.txt
testcase_gen_tool-1.0.1.dist-info/RECORD
