Metadata-Version: 2.4
Name: testcase-gen-tool
Version: 1.0.1
Summary: An automated test case generation tool that simplifies the process of creating test cases for software projects.
Requires-Python: >=3.12
Requires-Dist: gradio>=5.29.0
Requires-Dist: openpyxl>=3.1.5
Requires-Dist: pandas>=2.2.3
Requires-Dist: pypdf2>=3.0.1
Requires-Dist: python-docx>=1.1.2
Requires-Dist: requests>=2.32.3
